nchunk/__init__.py
nchunk/cli.py
nchunk/config.py
nchunk/empty.py
nchunk/errors.py
nchunk/progress.py
nchunk/uploader.py
nchunk/utils.py
nchunk-0.4.3.dist-info/METADATA
nchunk-0.4.3.dist-info/WHEEL
nchunk-0.4.3.dist-info/entry_points.txt
nchunk-0.4.3.dist-info/licenses/LICENSE
nchunk-0.4.3.dist-info/RECORD
