Metadata-Version: 2.4
Name: nchunk
Version: 0.4.3
Summary: Asynchronous chunked uploader for Nextcloud with Typer CLI and Rich progress bars
Project-URL: Homepage, https://github.com/Knyllahsyhn/nchunk
Project-URL: Source, https://github.com/Knyllahsyhn/nchunk
Project-URL: Tracker, https://github.com/Knyllahsyhn/nchunk/issues
Project-URL: CI, https://github.com/Knyllahsyhn/nchunk/actions
Author-email: Johannes Mueller <kex1.jml@gmail.com>
License-Expression: GPL-3.0
License-File: LICENSE
Keywords: async,cli,nextcloud,upload,webdav
Classifier: Environment :: Console
Classifier: Intended Audience :: Developers
Classifier: License :: OSI Approved :: GNU General Public License v3 (GPLv3)
Classifier: Programming Language :: Python :: 3
Classifier: Programming Language :: Python :: 3 :: Only
Classifier: Programming Language :: Python :: 3.11
Classifier: Programming Language :: Python :: 3.12
Classifier: Topic :: Internet :: File Transfer Protocol (FTP)
Classifier: Topic :: System :: Networking
Requires-Python: >=3.11
Requires-Dist: aiofiles>=23.2
Requires-Dist: aiohttp>=3.9
Requires-Dist: keyring>=24.3
Requires-Dist: python-dotenv>=1.0
Requires-Dist: rich>=13.7
Requires-Dist: typer[all]>=0.12
Provides-Extra: dev
Requires-Dist: aioresponses>=0.7; extra == 'dev'
Requires-Dist: pre-commit>=3.7; extra == 'dev'
Requires-Dist: pytest-asyncio>=0.23; extra == 'dev'
Requires-Dist: pytest>=8; extra == 'dev'
Requires-Dist: ruff>=0.4.3; extra == 'dev'
